README.md
setup.py
saltant/__init__.py
saltant/client.py
saltant/constants.py
saltant/exceptions.py
saltant/version.py
saltant/models/__init__.py
saltant/models/base_task_instance.py
saltant/models/base_task_type.py
saltant/models/container_task_instance.py
saltant/models/container_task_type.py
saltant/models/executable_task_instance.py
saltant/models/executable_task_type.py
saltant/models/resource.py
saltant/models/task_queue.py
saltant/models/task_whitelist.py
saltant/models/user.py
saltant_py.egg-info/PKG-INFO
saltant_py.egg-info/SOURCES.txt
saltant_py.egg-info/dependency_links.txt
saltant_py.egg-info/requires.txt
saltant_py.egg-info/top_level.txt